respparser/__init__.py
respparser/cli.py
respparser/parser.py
respparser-0.1.0.dist-info/METADATA
respparser-0.1.0.dist-info/WHEEL
respparser-0.1.0.dist-info/entry_points.txt
respparser-0.1.0.dist-info/RECORD
