Metadata-Version: 2.4
Name: respparser
Version: 0.1.0
Summary: Add your description here
Author-email: Joe Pasquantonio <joe.pasquantonio@gmail.com>
Requires-Python: >=3.11
Requires-Dist: click>=8.1.8
